repviz/__init__.py
repviz/hooks.py
repviz/inference.py
repviz/models.py
repviz/plots.py
repviz/registry.py
repviz/tools.py
repviz/utils.py
repviz-0.1.2.dist-info/METADATA
repviz-0.1.2.dist-info/WHEEL
repviz-0.1.2.dist-info/top_level.txt
repviz-0.1.2.dist-info/RECORD
