Metadata-Version: 2.4
Name: repviz
Version: 0.1.2
Summary: Add your description here
Requires-Python: >=3.11
Requires-Dist: scikit-learn>=1.6.1
Requires-Dist: seaborn>=0.13.2
Requires-Dist: torch>=2.6.0
